MANIFEST.in
setup.py
django_saber.egg-info/PKG-INFO
django_saber.egg-info/SOURCES.txt
django_saber.egg-info/dependency_links.txt
django_saber.egg-info/requires.txt
django_saber.egg-info/top_level.txt
djangosaber/__init__.py
djangosaber/__init__.pyc
djangosaber/cache.pyc
djangosaber/saber.py
djangosaber/saber.pyc
djangosaber/__pycache__/__init__.cpython-35.pyc
djangosaber/__pycache__/cache.cpython-35.pyc
djangosaber/__pycache__/saber.cpython-35.pyc
djangosaber/cache/__init__.py
djangosaber/cache/__init__.pyc
djangosaber/cache/inmemory_boxed.py
djangosaber/cache/threaded.py
djangosaber/cache/threaded.pyc