Metadata-Version: 1.0
Name: django-saber
Version: 0.6.1
Summary: Saber provides an in-memory replacement for the Django-ORM
Home-page: http://github.com/futurice/django-saber
Author: Jussi Vaihia
Author-email: jussi.vaihia@futurice.com
License: BSD
Keywords: django model orm replacement inmemory performance fast calculations
Platform: UNKNOWN
